{
	"cardType":83,
	"cardName":"Relay",
	"effText":"Charge: Draw 1 card, then discard 1 card.",
	"effects":[
		{
			"triggerData":
			{
				"triggerCondition":"Activate",
				"triggerRestriction":{
					"triggerRestrictions":["This Card Triggered","This Card Fits Restriction"],
					"cardRestriction":{
						"cardRestrictions":["Space Fits Restriction"],
						"spaceRestriction":
						{
							"spaceRestrictions":["Connected to Source by Cards Fitting Restriction"],
							"connectednessRestriction":
							{
								"cardRestrictions":["Subtypes Include","Board"],
								"subtypesInclude":["Conductor"]
							},
							"mustBeEmpty":false
						}
					}
				}
			},
			"subeffects":[
				{
					"$type":"KompasServer.Effects.DrawSubeffect, Assembly-CSharp"
				},
				{
					"$type":"KompasServer.Effects.CardTargetSubeffect, Assembly-CSharp",
					"cardRestriction":
					{
						"blurb":"Relay discard",
						"cardRestrictions":["Friendly","Hand"]
					}
				},
				{
					"$type":"KompasServer.Effects.DiscardSubeffect, Assembly-CSharp"
				}
			]
		}
	],
	"c":1,
	"spellTypes":["Enchant"],
	"subtypeText":"Chargeable Conductor"
}