{
	"cardType": 67,
	"cardName": "PH453R",
	"effText": "Nimble Evasive Golem.",
	"effects": [],
	"MovementRestriction": {
		"normalRestrictionsFromJson": [
			"Default",
			"Activated",
			"Can Move Enough Through Empty or Restricted Spaces"
		],
		"normalRestrictionsToIgnore": [
			"Can Move Enough Spaces"
		],
		"throughSpacesRestriction": {
			"spaceRestrictions": []
		}
	},
	"AttackRestriction": {
		"attackRestrictions": [
			"Default",
			"This is Activated"
		]
	},
	"keywords": [
		"Evasive"
	],
	"n": 3,
	"e": 3,
	"s": 10,
	"w": 3,
	"subtypes": [
		"Mech",
		"Golem"
	],
	"subtypeText": "Mech Golem"
}