{
	"cardType": 83,
	"cardName": "Wanderlust",
	"effText": "Choose a friendly summon. Any number of times: Reshuffle the last chosen character. Hand->summon one with up to 1 more S.",
	"effects": [
		{
			"triggerData": {
				"triggerCondition": "Play",
				"triggerRestriction": {
					"triggerRestrictions": [
						"This Card is Main Card"
					]
				}
			},
			"subeffects": [
				{
					"$type": "Subeffect:CardTarget:",
					"cardRestriction": {
						"blurb": "friendly character to wander",
						"cardRestrictions": [
							"Character",
							"Summoned"
						],
						"cardRestrictionElements": [
							{ "$type": "Core.CardRestriction:Friendly:" },
							{
								"$type": "Core.CardRestriction:Location:",
								"locations": [ "Board" ]
							}
						]
					}
				},
				{
					"$type": "Subeffect:SetXByTargetCardValue:",
					"cardValue": {
						"value": "S"
					},
					"xMultiplier": 1
				},
				{
					"$type": "Subeffect:Reshuffle:"
				},
				{
					"$type": "Subeffect:CardTarget:",
					"cardRestriction": {
						"blurb": "for Wanderlust to hand-summon",
						"cardRestrictions": [
							"Character"
						],
						"cardRestrictionElements": [
							{ "$type": "Core.CardRestriction:Friendly:" },
                            {
                                "$type": "Core.CardRestriction:Location:",
                                "locations": [ "Hand" ]
                            },
							{
								"$type": "Core.CardRestriction:CardValueFits:",
								"cardValue": { "value": "S" },
								"numberRestriction": { "elements": [{
									"$type": "Core.NumberRestriction:Compare:",
									"comparison": { "$type": "Relationships.Number:LessThanEqual:" },
									"other": { "$type": "Numbers:X:" }
								}]}
							}
						]
					},
					"xMultiplier": 1,
					"xModifier": 1
				},
				{
					"$type": "Subeffect:SpaceTarget:",
					"spaceRestriction": {
						"blurb": "where Wanderlust to hand-summon",
                        "spaceRestrictionElements": [
                            { "$type": "Core.SpaceRestriction:Empty:" },
                            {
                                "$type": "Core.SpaceRestriction:CanPlayCard:",
                                "toPlay": { "$type": "Cards:TargetIndex:" }
                            }
                        ]
					}
				},
				{
					"$type": "Subeffect:Play:"
				},
				{
					"$type": "Subeffect:ChooseOption:",
					"choiceBlurb": "Reshuffle to summon again?",
					"optionBlurbs": [
						"Yes",
						"No"
					],
					"jumpIndices": [
						1,
						100
					]
				}
			]
		}
	],
	"c": 1,
	"spellTypes": [
		"Simple"
	],
	"subtypeText": "Simple"
}