{
	"cardType":67,
	"cardName":"The General",
	"effText":"Once each friendly turn, you can pip decksummon any number of Warriors from your deck’s top 5 cards. Bottomdeck the rest.",
	"effects":[
		{
			"activationRestriction":{
				"activationRestrictionArray":[
					"Max Times Per Turn",
					"Friendly Turn",
					"Default"
				]
			},
			"subeffects":[
				{
					"$type":"KompasServer.Effects.SkipToEffectOnImpossibleSubeffect, Assembly-CSharp",
					"jumpIndices":[6]
				},
				{
					"$type":"KompasServer.Effects.ChooseFromListSaveRestSubeffect, Assembly-CSharp",
					"maxCanChoose":1,
					"cardRestriction":
					{
						"blurb":"Warrior for The General to recruit",
						"cardRestrictions":["Friendly","Deck","Is Character","Index<X","Subtypes Include","Can Be Played","Effect Controller can Afford Cost"],
						"subtypesInclude":["Warrior"]
					},
					"restRestriction":
					{
						"cardRestrictions":["Friendly","Deck","Index<X","Not Already Target"]
					},
					"listRestriction":{
						"listRestrictions":["Can Pay Cost","Min Can Choose"],
						"minCanChoose":1
					},
					"xModifier":5
				},
				{
					"$type":"KompasServer.Effects.SpaceTargetSubeffect, Assembly-CSharp",
					"spaceRestriction":
					{
						"blurb":"where for The General to recruit their Warrior",
						"spaceRestrictions":["Can Play Target to This Space"]
					}
				},
				{
					"$type":"KompasServer.Effects.PayPipsTargetCostSubeffect, Assembly-CSharp",
					"xMultiplier":1
				},
				{
					"$type":"KompasServer.Effects.PlaySubeffect, Assembly-CSharp"
				},
				{
					"$type":"KompasServer.Effects.LoopWhileHaveTargetsSubeffect, Assembly-CSharp",
					"delete":true,
					"jumpIndices":[2]
				},
				{
					"$type":"KompasServer.Effects.BottomdeckRestSubeffect, Assembly-CSharp"
				}
			]
		}
	],
	"n":1,
	"e":10,
	"s":10,
	"w":10,
	"subtypeText":"Swordguild Warrior"
}