{
	"blurb":"Wisp Turn Start",
	"triggerData":
	{
		"blurb":"Wisp Turn Start",
		"triggerCondition":"Turn Start",
		"triggerRestriction":{
			"triggerRestrictions":["This Card in Play"]
		}
	},
	"subeffects":[
		{
			"$type": "Subeffect:AutoTargetSpaceIdentity:",
			"subeffectSpaceIdentity": {
				"$type": "Gamestate.ManyCards:SelectFromMany:",
				"selector": { "$type": "KompasCore.Effects.Selectors.RandomSelector, Assembly-CSharp" },
				"spaces": {
					"$type": "Gamestate.ManySpaces:CompareDistance:",
					"distanceTo": { 
						"$type": "Subeffect.Space:PositionOf:",
						"whosePosition": { "$type": "Gamestate.Card:ThisCard:" }
					},
					"spaces": {
						"$type": "Gamestate.ManySpaces:PositionsOfEach:",
						"cards": {
							"$type": "Gamestate.ManyCards:FittingRestriction:",
							"cardRestriction": {
								"cardRestrictionElements": [ { "$type": "Core.CardRestriction:Enemy:" } ]
							}
						}
					}
				}
			}
		},
		{
			"$type": "Subeffect:AutoTargetSpaceIdentity:",
			"subeffectSpaceIdentity": {
				"$type": "Gamestate.Space:SelectFromMany:",
				"selector": { "$type": "KompasCore.Effects.Selectors.RandomSelector, Assembly-CSharp" },
				"spaces": {
					"$type": "Gamestate.ManySpaces:CompareDistance:",
					"distanceTo": { "$type": "Subeffect.Space:Target:" },
					"spaces": {
						"$type": "Gamestate.ManySpaces:AdjacentSpaces:",
						"adjacentTo": {
							"$type": "Subeffect.Space:PositionOf:",
							"whosePosition": { "$type": "Gamestate.Card:ThisCard:" }
						}
					}
				}
			}
		},
		{
			"$type": "Subeffect:TargetThis:"
		},
		{
			"$type":"Subeffect:Move:"
		}
	]	
}