{
	"cardType": 67,
	"cardName": "Repairman",
	"effText": "When an adjacent Structure survives losing E, heal it.",
	"effects": [
		{
            "blurb": "Repair",
			"triggerData": {
				"triggerCondition": "E Change",
				"triggerRestriction": {
					"triggerRestrictions": [
						"This Card in Play",
						"X Fits Restriction",
						"This Card is Main Card",
						"Main Card Fits Restriction After"
					],
					"xRestriction": {
						"numberRestrictions": [
							"<0"
						]
					},
					"nowRestriction": {
						"cardRestrictionElements": [
							{
								"$type": "Core.CardRestriction:Location:",
								"locations": [ "Board" ]
							},
							{
								"$type": "Core.CardRestriction:Subtypes:",
								"subtypes": [ "Structure" ]
							},
                            {
                                "$type": "Core.CardRestriction:PositionFitsRestriction:",
                                "spaceRestriction": {
									"spaceRestrictions": [
										"Adjacent to Source"
									]
                                }
                            }
						]
					}
				}
			},
			"subeffects": [
				{
					"$type": "Subeffect:TargetTriggeringCard:"
				},
				{
					"$type": "Subeffect:Heal:"
				}
			]
		}
	],
	"n": 1,
	"e": 1,
	"s": 1,
	"w": 1,
	"subtypeText": "Maya Craftsperson"
}